NasNas/__init__.py
NasNas/core/__init__.py
NasNas/core/app.py
NasNas/core/camera.py
NasNas/core/debug.py
NasNas/core/entities.py
NasNas/core/layers.py
NasNas/core/scenes.py
NasNas/core/sprites.py
NasNas/core/text.py
NasNas/core/transitions.py
NasNas/core/utils.py
NasNas/core/window.py
NasNas/data/__init__.py
NasNas/data/callbacks.py
NasNas/data/const.py
NasNas/data/game_obj.py
NasNas/data/keys.py
NasNas/data/rect.py
NasNas/data/shapes.py
NasNas/reslib/__init__.py
NasNas/reslib/resource_loader.py
NasNas/reslib/resource_manager.py
NasNas/reslib/resource_path.py
NasNas/reslib/tileset_manager.py
NasNas/tilemapping/__init__.py
NasNas/tilemapping/layers.py
NasNas/tilemapping/tiledmap.py
NasNas/tilemapping/tiles.py
NasNas/tilemapping/tilesets.py
NasNas/ui/__init__.py
NasNas/ui/buttons.py
NasNas/ui/menus.py
NasNas/ui/styles.py
NasNas-0.1.3.dist-info/LICENSE.md
NasNas-0.1.3.dist-info/METADATA
NasNas-0.1.3.dist-info/WHEEL
NasNas-0.1.3.dist-info/top_level.txt
NasNas-0.1.3.dist-info/RECORD
