Metadata-Version: 2.1
Name: NasNas
Version: 0.1.3
Summary: A simple game framework to get started quickly with python and sfml.
Home-page: https://github.com/Madour/pyNasNas
Author: Modar Nasser
Author-email: modar1999@gmail.com
License: UNKNOWN
Keywords: sfml,game dev,game engine,framework
Platform: UNKNOWN
Classifier: Development Status :: 3 - Alpha
Classifier: Intended Audience :: Developers
Classifier: License :: OSI Approved :: zlib/libpng License
Classifier: Programming Language :: Python :: 3
